grandturismo/__init__.py
grandturismo/intake/__init__.py
grandturismo/intake/listener.py
grandturismo/maps/__init__.py
grandturismo/maps/map.py
grandturismo/model/__init__.py
grandturismo/model/common.py
grandturismo/model/packet.py
grandturismo/security/__init__.py
grandturismo/security/decrypter.py
grandturismo/utils/__init__.py
grandturismo/utils/debug.py
grandturismo/utils/network_to_host.py
grandturismo/utils/settings.py
grandturismo-0.1.2.data/scripts/capture_race.py
grandturismo-0.1.2.data/scripts/main.py
grandturismo-0.1.2.data/scripts/reduce_map_size.py
grandturismo-0.1.2.data/scripts/visualize_direction_velocity.py
grandturismo-0.1.2.data/scripts/visualize_map.py
grandturismo-0.1.2.data/scripts/visualize_maps.py
grandturismo-0.1.2.dist-info/METADATA
grandturismo-0.1.2.dist-info/WHEEL
grandturismo-0.1.2.dist-info/top_level.txt
grandturismo-0.1.2.dist-info/RECORD
