Metadata-Version: 2.1
Name: grandturismo
Version: 0.1.2
Summary: Get Grand Turismo telemetry data from the PlayStation console
Author: Lucas Pettit
Author-email: lucaspettit64@gmail.com
License: MIT
Project-URL: Bug Tracker, https://github.com/lucaspettit/telempy/issues
Project-URL: Source Code, https://github.com/lucaspettit/telempy
Platform: Windows
Platform: Linux
Platform: Solaris
Platform: Mac OS-X
Platform: Unix
Requires-Python: >=3.7
Requires-Dist: salsa20
Requires-Dist: marshmallow-dataclass
Requires-Dist: marshmallow-enum
